find_mfs/__init__.py
find_mfs/core/__init__.py
find_mfs/core/algorithms.py
find_mfs/core/decomposer.py
find_mfs/core/finder.py
find_mfs/core/results.py
find_mfs/core/validator.py
find_mfs/data/__init__.py
find_mfs/data/ert_chnops.py
find_mfs/data/ert_chnops_halogens.py
find_mfs/isotopes/__init__.py
find_mfs/isotopes/config.py
find_mfs/isotopes/envelope.py
find_mfs/isotopes/results.py
find_mfs/utils/__init__.py
find_mfs/utils/filtering.py
find_mfs/utils/formulae.py
find_mfs/utils/mass_error.py
find_mfs-0.1.0.dist-info/licenses/LICENSE
find_mfs-0.1.0.dist-info/METADATA
find_mfs-0.1.0.dist-info/WHEEL
find_mfs-0.1.0.dist-info/top_level.txt
find_mfs-0.1.0.dist-info/RECORD
