Metadata-Version: 2.4
Name: find-mfs
Version: 0.1.0
Summary: A Python package implementing Bocker & Liptak's algorithm for finding molecular formulae from a given mass, as well as Kind and Fiehn's heuristics
Author-email: Mostafa Hagar <mostafa@150mL.com>
License: GPL-3.0-or-later
Project-URL: Homepage, https://github.com/mhagar/find-mfs
Project-URL: Documentation, https://github.com/mhagar/find-mfs#readme
Project-URL: Repository, https://github.com/mhagar/find-mfs
Project-URL: Issues, https://github.com/mhagar/find-mfs/issues
Keywords: mass spectrometry,molecular formula,accurate mass,chemistry,proteomics,metabolomics
Classifier: Development Status :: 3 - Alpha
Classifier: Intended Audience :: Science/Research
Classifier: License :: OSI Approved :: GNU General Public License v3 or later (GPLv3+)
Classifier: Programming Language :: Python :: 3
Classifier: Programming Language :: Python :: 3.10
Classifier: Programming Language :: Python :: 3.11
Classifier: Programming Language :: Python :: 3.12
Classifier: Topic :: Scientific/Engineering :: Chemistry
Requires-Python: >=3.10
License-File: LICENSE
Requires-Dist: molmass
Requires-Dist: numpy
Requires-Dist: numba
Requires-Dist: IsoSpecPy
Requires-Dist: scipy
Provides-Extra: dev
Requires-Dist: pytest>=8.3.5; extra == "dev"
Requires-Dist: pandas; extra == "dev"
Requires-Dist: matplotlib; extra == "dev"
Requires-Dist: jupyter; extra == "dev"
Dynamic: license-file
